LICENSE.txt
MANIFEST.in
README.md
setup.py
PyPTS.egg-info/PKG-INFO
PyPTS.egg-info/SOURCES.txt
PyPTS.egg-info/dependency_links.txt
PyPTS.egg-info/top_level.txt
pypts/__init__.py
pypts/io.py
pypts/tgen.py
pypts/tissue.py
pypts/tviz.py
pypts/tgens/__init__.py
pypts/tgens/four_cells.py
pypts/tgens/hexagons.py
pypts/tgens/squares.py
pypts/tgens/tissue_293.py