Metadata-Version: 1.0
Name: PyPTS
Version: 0.2.5
Summary: Python toolbox for plant tissue simulation prototypes
Home-page: https://pypi.python.org/pypi/PyPTS/
Author: Przemyslaw Klosiewicz
Author-email: przemek.klosiewicz@gmail.com
License: BSD
Platform: UNKNOWN
